{"about_the_game":"","background":"https://store.akamai.steamstatic.com/images/storepagebackground/app/1891100?t=1644262475","background_raw":"https://store.akamai.steamstatic.com/images/storepagebackground/app/1891100?t=1644262475","capsule_image":"https://shared.akamai.steamstatic.com/store_item_assets/steam/apps/1891100/capsule_231x87.jpg?t=1644262475","capsule_imagev5":"https://shared.akamai.steamstatic.com/store_item_assets/steam/apps/1891100/capsule_184x69.jpg?t=1644262475","content_descriptors":{"ids":[],"notes":null},"detailed_description":"","header_image":"https://shared.akamai.steamstatic.com/store_item_assets/steam/apps/1891100/header.jpg?t=1644262475","is_free":false,"linux_requirements":[],"mac_requirements":[],"name":"Molecoole Playtest","package_groups":[],"pc_requirements":[],"platforms":{"linux":false,"mac":false,"windows":true},"ratings":null,"release_date":{"coming_soon":false,"date":"7 Feb, 2022"},"required_age":0,"screenshots":[{"id":0,"path_full":"https://shared.akamai.steamstatic.com/store_item_assets/steam/apps/1891100/ss_d477dac70b5e749f253c65e074f41cac5f187204.1920x1080.jpg?t=1644262475","path_thumbnail":"https://shared.akamai.steamstatic.com/store_item_assets/steam/apps/1891100/ss_d477dac70b5e749f253c65e074f41cac5f187204.600x338.jpg?t=1644262475"}],"short_description":"","steam_appid":1891100,"support_info":{"email":"","url":""},"type":"game","website":null}