{"about_the_game":"","background":"https://store.akamai.steamstatic.com/images/storepagebackground/app/1983030?t=1669292826","background_raw":"https://store.akamai.steamstatic.com/images/storepagebackground/app/1983030?t=1669292826","capsule_image":"https://shared.akamai.steamstatic.com/store_item_assets/steam/apps/1983030/capsule_231x87.jpg?t=1669292826","capsule_imagev5":"https://shared.akamai.steamstatic.com/store_item_assets/steam/apps/1983030/capsule_184x69.jpg?t=1669292826","categories":[{"description":"Game demo","id":10}],"content_descriptors":{"ids":[2,5],"notes":"Cartoon violence & blood"},"detailed_description":"","developers":["Mushy Jukebox"],"fullgame":{"appid":"1934540","name":"Madville+"},"header_image":"https://shared.akamai.steamstatic.com/store_item_assets/steam/apps/1983030/header.jpg?t=1669292826","is_free":true,"linux_requirements":[],"mac_requirements":[],"name":"Madville+ Demo","package_groups":[],"pc_requirements":[],"platforms":{"linux":false,"mac":false,"windows":true},"publishers":["Mushy Jukebox"],"ratings":null,"release_date":{"coming_soon":false,"date":"2 May, 2022"},"required_age":0,"short_description":"","steam_appid":1983030,"support_info":{"email":"","url":"http://mushyjukebox.com/"},"type":"demo","website":null}