{"about_the_game":"<h2 class=\"bb_tag\">\u672cDLC\u4e3a\u300a\u89c5\u5149\u300b\u7b2c\u4e00\u7ae0\u539f\u753b\u96c6\uff0c\u4e5f\u53ef\u8d2d\u4e70\u8be5dlc\u652f\u6301\u4f5c\u8005\u54e6~</h2>DLC\u5185\u5bb9\u4e3a\u539f\u753b\u96c6\u6587\u4ef6\uff0c\u5185\u542b\u6e38\u620f\u5185\u51fa\u73b0\u8fc7\u7684\u5927\u90e8\u5206\u7d20\u6750\uff1a<br>\u2460CG\u3001\u4e8b\u4ef6\u63d2\u56fe87\u5f20<br>\u2461\u573a\u666f22\u5f20<br>\u2462\u9644\u8d60\u623f\u95f4\u5185\u5bb925\u5f20<br>\u2463\u7acb\u7ed814\u5f20<br>\u2464\u89d2\u8272\u4e00\u89c8<br><br>\u53e6\u5916\uff0c\u8fd8\u67096\u5f20\u6e38\u620f\u5185\u89d2\u8272\u5f62\u8c61\u7684\u5b9e\u7528\u8868\u60c5\u5305XD<br>\u4ee5\u4e0a\uff0c\u795d\u60a8\u4f7f\u7528\u6109\u5feb~<h2 class=\"bb_tag\">\u4f5c\u8005\u7559\u8a00</h2>\u674e\u72d7\u86cb\uff1a\u5927\u5bb6\u597d~\u6211\u662f\u4e3b\u5236\u4f5c\u4ebalidogegg\uff0c\u672c\u4f5c\u662f\u7ecf\u300a\u6253\u5de5\u5427\uff01\u5929\u4f7f\u9171\u300b\u540e\u7684\u7b2c\u4e8c\u4e2a\u6e38\u620f\u4f5c\u54c1\uff0c\u6bd4\u8d77\u524d\u4f5c\u505a\u4e86\u66f4\u591a\u52aa\u529b\uff0c\u662f\u4e00\u4e2a\u6bd4\u8f83\u4fa7\u91cd\u5267\u60c5\u7684rpg\u3002<br>\u8fd9\u4f5c\u7684\u7f8e\u672f\u4e5f\u8fdb\u884c\u4e86\u5f88\u591a\u7684\u5c1d\u8bd5\u548c\u5347\u7ea7\uff01<br>\u5927\u5bb6\u559c\u6b22\u7684\u8bdd\u53ef\u4ee5\u8d2d\u5165dlc\u652f\u6301\u6211~<br><br>\u4f0a\u67da\uff1a\u5927\u5bb6\u597d~\u6211\u662f\u6478\u9c7c\u5236\u4f5c\u4eba\u4f0a\u67da\uff01\u548c\u72d7\u86cb\u5408\u4f5c\u505a\u4e86\u8fd9\u6b3e\u6e38\u620f\uff0c\u56e0\u4e3a\u75ab\u60c5\u7684\u5173\u7cfb\u5728\u5bb6\u91cc\u8fb9\u4e0a\u8bfe\u8fb9\u505a\u6e38\u620f\u6478\u4e86\u4e00\u5e74\u591a\u7ec8\u4e8e\u51fa\u6765\u5566\uff0c\u6b22\u8fce\u5927\u5bb6\u6765\u73a9\u5440\uff01\u559c\u6b22\u7684\u8bdd\u8d2d\u4e70dlc\u652f\u6301\u6211\u4eec\u5427~<br><br><img class=\"bb_img\" src=\"https://shared.akamai.steamstatic.com/store_item_assets/steam/apps/2365930/extras/pic.png?t=1679716734\" />","background":"https://store.akamai.steamstatic.com/images/storepagebackground/app/2365930?t=1679716734","background_raw":"https://store.akamai.steamstatic.com/images/storepagebackground/app/2365930?t=1679716734","capsule_image":"https://shared.akamai.steamstatic.com/store_item_assets/steam/apps/2365930/capsule_231x87.jpg?t=1679716734","capsule_imagev5":"https://shared.akamai.steamstatic.com/store_item_assets/steam/apps/2365930/capsule_184x69.jpg?t=1679716734","categories":[{"description":"Single-player","id":2},{"description":"Downloadable Content","id":21}],"content_descriptors":{"ids":[],"notes":null},"detailed_description":"<h1>\u4f7f\u7528\u8bf4\u660e</h1><p>1.\u9996\u5148\u6253\u5f00\u6e38\u620f\u4e0b\u8f7d\u76ee\u5f55\u6587\u4ef6\u5939~\uff08\u53ef\u4ee5\u76f4\u63a5\u5728steam\u5e93\u9009\u62e9\u3010\u6d4f\u89c8\u672c\u5730\u6587\u4ef6\u3011\uff09<br>2.\u627e\u5230\u3010DLC\u3011\u6587\u4ef6\u5939\uff0c\u5373\u53ef\u83b7\u5f97\u6587\u4ef6~<br><br>\u539f\u753b\u96c6\u6587\u4ef6\u4ec5\u4f9b\u975e\u5546\u4e1a\u7528\u9014\uff0c\u4e0d\u53ef\u4ee5\u5546\u7528\u6216\u8005\u7528\u4e8e\u4e0e\u672c\u4f5c\u65e0\u5173\u7684\u4f5c\u54c1\u4e2d\u54e6\uff0c\u611f\u8c22\u652f\u6301~</p><br><h1>About the Game</h1><h2 class=\"bb_tag\">\u672cDLC\u4e3a\u300a\u89c5\u5149\u300b\u7b2c\u4e00\u7ae0\u539f\u753b\u96c6\uff0c\u4e5f\u53ef\u8d2d\u4e70\u8be5dlc\u652f\u6301\u4f5c\u8005\u54e6~</h2>DLC\u5185\u5bb9\u4e3a\u539f\u753b\u96c6\u6587\u4ef6\uff0c\u5185\u542b\u6e38\u620f\u5185\u51fa\u73b0\u8fc7\u7684\u5927\u90e8\u5206\u7d20\u6750\uff1a<br>\u2460CG\u3001\u4e8b\u4ef6\u63d2\u56fe87\u5f20<br>\u2461\u573a\u666f22\u5f20<br>\u2462\u9644\u8d60\u623f\u95f4\u5185\u5bb925\u5f20<br>\u2463\u7acb\u7ed814\u5f20<br>\u2464\u89d2\u8272\u4e00\u89c8<br><br>\u53e6\u5916\uff0c\u8fd8\u67096\u5f20\u6e38\u620f\u5185\u89d2\u8272\u5f62\u8c61\u7684\u5b9e\u7528\u8868\u60c5\u5305XD<br>\u4ee5\u4e0a\uff0c\u795d\u60a8\u4f7f\u7528\u6109\u5feb~<h2 class=\"bb_tag\">\u4f5c\u8005\u7559\u8a00</h2>\u674e\u72d7\u86cb\uff1a\u5927\u5bb6\u597d~\u6211\u662f\u4e3b\u5236\u4f5c\u4ebalidogegg\uff0c\u672c\u4f5c\u662f\u7ecf\u300a\u6253\u5de5\u5427\uff01\u5929\u4f7f\u9171\u300b\u540e\u7684\u7b2c\u4e8c\u4e2a\u6e38\u620f\u4f5c\u54c1\uff0c\u6bd4\u8d77\u524d\u4f5c\u505a\u4e86\u66f4\u591a\u52aa\u529b\uff0c\u662f\u4e00\u4e2a\u6bd4\u8f83\u4fa7\u91cd\u5267\u60c5\u7684rpg\u3002<br>\u8fd9\u4f5c\u7684\u7f8e\u672f\u4e5f\u8fdb\u884c\u4e86\u5f88\u591a\u7684\u5c1d\u8bd5\u548c\u5347\u7ea7\uff01<br>\u5927\u5bb6\u559c\u6b22\u7684\u8bdd\u53ef\u4ee5\u8d2d\u5165dlc\u652f\u6301\u6211~<br><br>\u4f0a\u67da\uff1a\u5927\u5bb6\u597d~\u6211\u662f\u6478\u9c7c\u5236\u4f5c\u4eba\u4f0a\u67da\uff01\u548c\u72d7\u86cb\u5408\u4f5c\u505a\u4e86\u8fd9\u6b3e\u6e38\u620f\uff0c\u56e0\u4e3a\u75ab\u60c5\u7684\u5173\u7cfb\u5728\u5bb6\u91cc\u8fb9\u4e0a\u8bfe\u8fb9\u505a\u6e38\u620f\u6478\u4e86\u4e00\u5e74\u591a\u7ec8\u4e8e\u51fa\u6765\u5566\uff0c\u6b22\u8fce\u5927\u5bb6\u6765\u73a9\u5440\uff01\u559c\u6b22\u7684\u8bdd\u8d2d\u4e70dlc\u652f\u6301\u6211\u4eec\u5427~<br><br><img class=\"bb_img\" src=\"https://shared.akamai.steamstatic.com/store_item_assets/steam/apps/2365930/extras/pic.png?t=1679716734\" />","developers":["\u8393\u8393\u52a8\u7269\u56ed"],"fullgame":{"appid":"2305480","name":"\u89c5\u5149\uff1a\u7b2c\u4e00\u7ae0 - Seeking Light : Chapter 1"},"genres":[{"description":"Casual","id":"4"},{"description":"Indie","id":"23"},{"description":"RPG","id":"3"},{"description":"Simulation","id":"28"}],"header_image":"https://shared.akamai.steamstatic.com/store_item_assets/steam/apps/2365930/header.jpg?t=1679716734","is_free":false,"linux_requirements":[],"mac_requirements":[],"name":"\u89c5\u5149\uff1a\u7b2c\u4e00\u7ae0 - \u539f\u753b\u96c6","package_groups":[{"description":"","display_type":0,"is_recurring_subscription":"false","name":"default","save_text":"","selection_text":"Select a purchase option","subs":[{"can_get_free_license":"0","is_free_license":false,"option_description":"","option_text":"\u89c5\u5149\uff1a\u7b2c\u4e00\u7ae0 - \u539f\u753b\u96c6 - $2.99 USD","packageid":850265,"percent_savings":0,"percent_savings_text":" ","price_in_cents_with_discount":299}],"title":"Buy \u89c5\u5149\uff1a\u7b2c\u4e00\u7ae0 - \u539f\u753b\u96c6"}],"packages":[850265],"pc_requirements":{"minimum":"<strong>Minimum:</strong><br><ul class=\"bb_ul\"><li><strong>OS:</strong> \u4efb\u610f\u7248\u672cWindows<br></li><li><strong>Processor:</strong> \u7535\u8111\u80fd\u5f00\u673a\u5c31\u597d<br></li><li><strong>Memory:</strong> 512 MB RAM<br></li><li><strong>Graphics:</strong> \u5c4f\u5e55\u80fd\u663e\u793a\u5c31\u884c<br></li><li><strong>Storage:</strong> 1 GB available space<br></li><li><strong>Sound Card:</strong> \u53ef\u4ee5\u53d1\u51fa\u58f0\u90fd\u6210</li></ul>","recommended":"<strong>Recommended:</strong><br><ul class=\"bb_ul\"><li><strong>OS *:</strong> Windows XP/Vista/7/8/8.1/10<br></li><li><strong>Processor:</strong> Intel I3/I5/I7<br></li><li><strong>Memory:</strong> 512 MB RAM<br></li><li><strong>Graphics:</strong> nVidia GT1030<br></li><li><strong>Storage:</strong> 1 GB available space<br></li><li><strong>Sound Card:</strong> Realtek</li></ul>"},"platforms":{"linux":false,"mac":false,"windows":true},"price_overview":{"currency":"USD","discount_percent":0,"final":299,"final_formatted":"$2.99 USD","initial":299,"initial_formatted":""},"publishers":["Eternal Dream"],"ratings":{"dejus":{"descriptors":"Conte\u00fado sexual\r\nViol\u00eancia","rating":"12","required_age":"12","use_age_gate":"true"},"steam_germany":{"banned":"0","descriptors":"Sexuelle Andeutungen","rating":"12","rating_generated":"1","required_age":"12","use_age_gate":"0"}},"release_date":{"coming_soon":false,"date":"24 Mar, 2023"},"required_age":0,"screenshots":[{"id":0,"path_full":"https://shared.akamai.steamstatic.com/store_item_assets/steam/apps/2365930/ss_6417296cb242aef201eedd650f2779cf491a488a.1920x1080.jpg?t=1679716734","path_thumbnail":"https://shared.akamai.steamstatic.com/store_item_assets/steam/apps/2365930/ss_6417296cb242aef201eedd650f2779cf491a488a.600x338.jpg?t=1679716734"},{"id":1,"path_full":"https://shared.akamai.steamstatic.com/store_item_assets/steam/apps/2365930/ss_4822d34eba3fde1557562c0c1f74f96860165d43.1920x1080.jpg?t=1679716734","path_thumbnail":"https://shared.akamai.steamstatic.com/store_item_assets/steam/apps/2365930/ss_4822d34eba3fde1557562c0c1f74f96860165d43.600x338.jpg?t=1679716734"}],"short_description":"\u672cDLC\u4e3a\u300a\u89c5\u5149\u300b\u7b2c\u4e00\u7ae0\u539f\u753b\u96c6\uff0c\u4e5f\u53ef\u8d2d\u4e70\u8be5dlc\u652f\u6301\u4f5c\u8005\u54e6~","steam_appid":2365930,"support_info":{"email":"1172037740@qq.com","url":""},"supported_languages":"Simplified Chinese","type":"dlc","website":"https://space.bilibili.com/1995649"}