{"about_the_game":"This is a set of game UI elements.<br>Quick theme changer plugin for Tyrano Builder (for 1280x720px) is also included. The system design can be easily replaced.<br><br>Rasterized PSD files are included for editing.<br><br>Use outside of Tyrano Builder is also acceptable.<br><br>\u25c6 How to Use \u25c6<br><br>\u25a0TyranoBuilder V2.04 or later (Recommended!)<br><br>When you purchase the DLC, the Quick theme changer plugin is automatically registered.<br><br>It can be used from Project -&gt; UI Theme Batch Conversion in the top menu bar. <br>To obtain the editable bonus data, click &quot;Output Asset Data for Editing&quot; on the same screen. <br><br>\u25a0Tyrano Builder V2.03 or earlier <br>When you purchase DLC, various data will be stored in a folder called &quot;dlc&quot; in the installation folder.<br>The bonus data is located in &quot;theme/[ID name of purchased DLC]/edit_data&quot;, so copy it to your favorite location and use it.<br><br>Previous versions can still use Quick theme changer plugins.<br>Copy the folder in &quot;append/[ID name of purchased DLC]&quot; in the bonus data to the following location.<br><br>\u30fbWindows<br>From TyranoBuilder installation folder, resources -&gt; app -&gt; ext -&gt; theme<br>Copy to this folder.<br><br>\u30fbMac<br>Right click on TyranoBuilder.app -&gt; Show package contents -&gt; Resources -&gt; app -&gt; ext -&gt; theme<br><br><br>\u25c6 TERMS OF USE \u25c6<br>You may use materials for games, applications, videos, illustrations, etc. <br>\u3000\u30fbFree games, shareware games, commercial projects, adult contents, derivative works, anything is OK.<br>\u3000\u30fbMay also be used for competition entries (with or without prize money).<br>\u3000\u30fbUse outside of Tyrano Builder is also acceptable.<br><br>\u3010MODIFICATION OF MATERIALS\u3011<br>\u3000\u30fbYou are free to modify this product. Customize it for your ease of use.<br><br>\u3010PROHIBITED USES\u3011<br>\u3000\u30fbRedistribution or reselling of materials as is<br>\u3000\u30fbPlagiarism of materials, false representation of authorship<br>\u3000\u30fbUse in which materials themselves have commercial value (including cases where materials are modified)<br>\u3000\u30fbUse in contents that are offensive to public order and morals, or that defames a specific company or organizational group, and harms its honor or credibility<br><br>\u3010USAGE REPORT &amp; COPYRIGHT NOTICE\u3011<br>\u3000\u30fbNo usage report is required.<br>\u3000\u30fbNo copyright notice is required.<br>\u3000\u30fbCopyright for this product is not relinquished.<br><br>\u3010DISCLAIMER\u3011<br>\u3000The creator is not responsible for any damage or loss caused by the use of this product. Please note that this product is intended to be used only by those who agree to this.<br><br>\u3010Author\u3011<br><br>\u25a0Publisher<br>STRIKEWORKS<br><br>\u25a0Developper<br>KUUSOU-KYOKUSEN<br><br>We borrowed materials to create the introductory images. <br>These are not included in this product.<br><br>\u3010CHARACTER ILLUSTRATION RESOURCES\u3011<br>\u3000\u308f\u305f\u304a\u304d\u3070<br><br>\u3010ILLUSTRATION RESOURCES\u3011<br>   \u4e03\u4e09\u3086\u304d\u306e\u30a2\u30c8\u30ea\u30a8<br><br>\u3010PHOTO RESOURCES\u3011<br>  Pixabay<br>  \u667a\u4e4b\u30bd\u30d5\u30c8","background":"https://store.akamai.steamstatic.com/images/storepagebackground/app/2408851?t=1684496716","background_raw":"https://store.akamai.steamstatic.com/images/storepagebackground/app/2408851?t=1684496716","capsule_image":"https://shared.akamai.steamstatic.com/store_item_assets/steam/apps/2408851/capsule_231x87.jpg?t=1684496716","capsule_imagev5":"https://shared.akamai.steamstatic.com/store_item_assets/steam/apps/2408851/capsule_184x69.jpg?t=1684496716","categories":[{"description":"Downloadable Content","id":21}],"content_descriptors":{"ids":[],"notes":null},"detailed_description":"This is a set of game UI elements.<br>Quick theme changer plugin for Tyrano Builder (for 1280x720px) is also included. The system design can be easily replaced.<br><br>Rasterized PSD files are included for editing.<br><br>Use outside of Tyrano Builder is also acceptable.<br><br>\u25c6 How to Use \u25c6<br><br>\u25a0TyranoBuilder V2.04 or later (Recommended!)<br><br>When you purchase the DLC, the Quick theme changer plugin is automatically registered.<br><br>It can be used from Project -&gt; UI Theme Batch Conversion in the top menu bar. <br>To obtain the editable bonus data, click &quot;Output Asset Data for Editing&quot; on the same screen. <br><br>\u25a0Tyrano Builder V2.03 or earlier <br>When you purchase DLC, various data will be stored in a folder called &quot;dlc&quot; in the installation folder.<br>The bonus data is located in &quot;theme/[ID name of purchased DLC]/edit_data&quot;, so copy it to your favorite location and use it.<br><br>Previous versions can still use Quick theme changer plugins.<br>Copy the folder in &quot;append/[ID name of purchased DLC]&quot; in the bonus data to the following location.<br><br>\u30fbWindows<br>From TyranoBuilder installation folder, resources -&gt; app -&gt; ext -&gt; theme<br>Copy to this folder.<br><br>\u30fbMac<br>Right click on TyranoBuilder.app -&gt; Show package contents -&gt; Resources -&gt; app -&gt; ext -&gt; theme<br><br><br>\u25c6 TERMS OF USE \u25c6<br>You may use materials for games, applications, videos, illustrations, etc. <br>\u3000\u30fbFree games, shareware games, commercial projects, adult contents, derivative works, anything is OK.<br>\u3000\u30fbMay also be used for competition entries (with or without prize money).<br>\u3000\u30fbUse outside of Tyrano Builder is also acceptable.<br><br>\u3010MODIFICATION OF MATERIALS\u3011<br>\u3000\u30fbYou are free to modify this product. Customize it for your ease of use.<br><br>\u3010PROHIBITED USES\u3011<br>\u3000\u30fbRedistribution or reselling of materials as is<br>\u3000\u30fbPlagiarism of materials, false representation of authorship<br>\u3000\u30fbUse in which materials themselves have commercial value (including cases where materials are modified)<br>\u3000\u30fbUse in contents that are offensive to public order and morals, or that defames a specific company or organizational group, and harms its honor or credibility<br><br>\u3010USAGE REPORT &amp; COPYRIGHT NOTICE\u3011<br>\u3000\u30fbNo usage report is required.<br>\u3000\u30fbNo copyright notice is required.<br>\u3000\u30fbCopyright for this product is not relinquished.<br><br>\u3010DISCLAIMER\u3011<br>\u3000The creator is not responsible for any damage or loss caused by the use of this product. Please note that this product is intended to be used only by those who agree to this.<br><br>\u3010Author\u3011<br><br>\u25a0Publisher<br>STRIKEWORKS<br><br>\u25a0Developper<br>KUUSOU-KYOKUSEN<br><br>We borrowed materials to create the introductory images. <br>These are not included in this product.<br><br>\u3010CHARACTER ILLUSTRATION RESOURCES\u3011<br>\u3000\u308f\u305f\u304a\u304d\u3070<br><br>\u3010ILLUSTRATION RESOURCES\u3011<br>   \u4e03\u4e09\u3086\u304d\u306e\u30a2\u30c8\u30ea\u30a8<br><br>\u3010PHOTO RESOURCES\u3011<br>  Pixabay<br>  \u667a\u4e4b\u30bd\u30d5\u30c8","developers":["STRIKEWORKS"],"fullgame":{"appid":"345370","name":"TyranoBuilder Visual Novel Studio"},"genres":[{"description":"Utilities","id":"57"},{"description":"Game Development","id":"60"}],"header_image":"https://shared.akamai.steamstatic.com/store_item_assets/steam/apps/2408851/header.jpg?t=1684496716","is_free":false,"legal_notice":"\u00a9 STRIKEWORKS, \u00a9 KUUSOU-KYOKUSEN","linux_requirements":{"minimum":"<strong>Minimum:</strong><br><ul class=\"bb_ul\"></ul>","recommended":"<strong>Recommended:</strong><br><ul class=\"bb_ul\"></ul>"},"mac_requirements":{"minimum":"<strong>Minimum:</strong><br><ul class=\"bb_ul\"><li><strong>Additional Notes:</strong> System supporting Tyrano Builder</li></ul>","recommended":"<strong>Recommended:</strong><br><ul class=\"bb_ul\"><li><strong>Additional Notes:</strong> System supporting Tyrano Builder</li></ul>"},"name":"Tyrano Builder - Visual Novel GUI Pack #3 Color-Blue [kopanda UI]","package_groups":[{"description":"","display_type":0,"is_recurring_subscription":"false","name":"default","save_text":"","selection_text":"Select a purchase option","subs":[{"can_get_free_license":"0","is_free_license":false,"option_description":"","option_text":"Tyrano Builder - Visual Novel GUI Pack #3 Color-Blue [kopanda UI] - $5.99 USD","packageid":866843,"percent_savings":0,"percent_savings_text":" ","price_in_cents_with_discount":599}],"title":"Buy Tyrano Builder - Visual Novel GUI Pack #3 Color-Blue [kopanda UI]"}],"packages":[866843],"pc_requirements":{"minimum":"<strong>Minimum:</strong><br><ul class=\"bb_ul\"><li>Requires a 64-bit processor and operating system<br></li><li><strong>Additional Notes:</strong> System supporting Tyrano Builder</li></ul>","recommended":"<strong>Recommended:</strong><br><ul class=\"bb_ul\"><li>Requires a 64-bit processor and operating system<br></li><li><strong>Additional Notes:</strong> System supporting Tyrano Builder</li></ul>"},"platforms":{"linux":false,"mac":true,"windows":true},"price_overview":{"currency":"USD","discount_percent":0,"final":599,"final_formatted":"$5.99 USD","initial":599,"initial_formatted":""},"publishers":["STRIKEWORKS"],"ratings":{"dejus":{"rating":"l"},"steam_germany":{"banned":"0","descriptors":"","rating":"0","rating_generated":"1","required_age":"0","use_age_gate":"0"}},"release_date":{"coming_soon":false,"date":"19 May, 2023"},"required_age":0,"screenshots":[{"id":0,"path_full":"https://shared.akamai.steamstatic.com/store_item_assets/steam/apps/2408851/ss_c0e3fa2759f9e5fdebc0d7a263a0da6c8ccd872a.1920x1080.jpg?t=1684496716","path_thumbnail":"https://shared.akamai.steamstatic.com/store_item_assets/steam/apps/2408851/ss_c0e3fa2759f9e5fdebc0d7a263a0da6c8ccd872a.600x338.jpg?t=1684496716"},{"id":1,"path_full":"https://shared.akamai.steamstatic.com/store_item_assets/steam/apps/2408851/ss_a4a1ce60274106feaf4e94abcb6d77ce317742d4.1920x1080.jpg?t=1684496716","path_thumbnail":"https://shared.akamai.steamstatic.com/store_item_assets/steam/apps/2408851/ss_a4a1ce60274106feaf4e94abcb6d77ce317742d4.600x338.jpg?t=1684496716"},{"id":2,"path_full":"https://shared.akamai.steamstatic.com/store_item_assets/steam/apps/2408851/ss_b4b7995c439fc3e38145abdc321cce47dc3edf9e.1920x1080.jpg?t=1684496716","path_thumbnail":"https://shared.akamai.steamstatic.com/store_item_assets/steam/apps/2408851/ss_b4b7995c439fc3e38145abdc321cce47dc3edf9e.600x338.jpg?t=1684496716"},{"id":3,"path_full":"https://shared.akamai.steamstatic.com/store_item_assets/steam/apps/2408851/ss_c3e2fac34c84e965407f8e7cf4a6494cb368488b.1920x1080.jpg?t=1684496716","path_thumbnail":"https://shared.akamai.steamstatic.com/store_item_assets/steam/apps/2408851/ss_c3e2fac34c84e965407f8e7cf4a6494cb368488b.600x338.jpg?t=1684496716"},{"id":4,"path_full":"https://shared.akamai.steamstatic.com/store_item_assets/steam/apps/2408851/ss_016d052331e68f78c2bc75cda0284bace713d56e.1920x1080.jpg?t=1684496716","path_thumbnail":"https://shared.akamai.steamstatic.com/store_item_assets/steam/apps/2408851/ss_016d052331e68f78c2bc75cda0284bace713d56e.600x338.jpg?t=1684496716"},{"id":5,"path_full":"https://shared.akamai.steamstatic.com/store_item_assets/steam/apps/2408851/ss_55902d23a864e4a5e88a4126e1ec3d8758ccaa61.1920x1080.jpg?t=1684496716","path_thumbnail":"https://shared.akamai.steamstatic.com/store_item_assets/steam/apps/2408851/ss_55902d23a864e4a5e88a4126e1ec3d8758ccaa61.600x338.jpg?t=1684496716"},{"id":6,"path_full":"https://shared.akamai.steamstatic.com/store_item_assets/steam/apps/2408851/ss_91958064ea1798826494602d43f1b10c46eb8b4a.1920x1080.jpg?t=1684496716","path_thumbnail":"https://shared.akamai.steamstatic.com/store_item_assets/steam/apps/2408851/ss_91958064ea1798826494602d43f1b10c46eb8b4a.600x338.jpg?t=1684496716"},{"id":7,"path_full":"https://shared.akamai.steamstatic.com/store_item_assets/steam/apps/2408851/ss_131296578f8a0e8e711dcbfdc5d532c3d7313ae4.1920x1080.jpg?t=1684496716","path_thumbnail":"https://shared.akamai.steamstatic.com/store_item_assets/steam/apps/2408851/ss_131296578f8a0e8e711dcbfdc5d532c3d7313ae4.600x338.jpg?t=1684496716"},{"id":8,"path_full":"https://shared.akamai.steamstatic.com/store_item_assets/steam/apps/2408851/ss_95d0beea524861bd8adadb784c32bef8f2a893b5.1920x1080.jpg?t=1684496716","path_thumbnail":"https://shared.akamai.steamstatic.com/store_item_assets/steam/apps/2408851/ss_95d0beea524861bd8adadb784c32bef8f2a893b5.600x338.jpg?t=1684496716"},{"id":9,"path_full":"https://shared.akamai.steamstatic.com/store_item_assets/steam/apps/2408851/ss_2255d1f97131d2f04b74538c07d0bdb98c885f22.1920x1080.jpg?t=1684496716","path_thumbnail":"https://shared.akamai.steamstatic.com/store_item_assets/steam/apps/2408851/ss_2255d1f97131d2f04b74538c07d0bdb98c885f22.600x338.jpg?t=1684496716"},{"id":10,"path_full":"https://shared.akamai.steamstatic.com/store_item_assets/steam/apps/2408851/ss_d2acb4543506708a75e334e9b6521aaad3f8c4aa.1920x1080.jpg?t=1684496716","path_thumbnail":"https://shared.akamai.steamstatic.com/store_item_assets/steam/apps/2408851/ss_d2acb4543506708a75e334e9b6521aaad3f8c4aa.600x338.jpg?t=1684496716"},{"id":11,"path_full":"https://shared.akamai.steamstatic.com/store_item_assets/steam/apps/2408851/ss_491febffb3972b380f911d49a02e80138cfc2824.1920x1080.jpg?t=1684496716","path_thumbnail":"https://shared.akamai.steamstatic.com/store_item_assets/steam/apps/2408851/ss_491febffb3972b380f911d49a02e80138cfc2824.600x338.jpg?t=1684496716"}],"short_description":"This is a set of game UI elements. Quick theme changer plugin for Tyrano Builder (for 1280x720px) is also included. The system design can be easily replaced. Rasterized PSD files are included for editing.","steam_appid":2408851,"support_info":{"email":"tyrano.official@gmail.com","url":"https://tyranobuilder.com"},"supported_languages":"English, Japanese","type":"dlc","website":"https://tyranobuilder.com"}