{"about_the_game":"","background":"https://store.akamai.steamstatic.com/images/storepagebackground/app/2821430?t=1716663613","background_raw":"https://store.akamai.steamstatic.com/images/storepagebackground/app/2821430?t=1716663613","capsule_image":"https://shared.akamai.steamstatic.com/store_item_assets/steam/apps/2821430/capsule_231x87.jpg?t=1716663613","capsule_imagev5":"https://shared.akamai.steamstatic.com/store_item_assets/steam/apps/2821430/capsule_184x69.jpg?t=1716663613","categories":[{"description":"Single-player","id":2},{"description":"Game demo","id":10}],"content_descriptors":{"ids":[2,5],"notes":"The game is a visual novel, mature content is only written about - no visual form of mature content in the game."},"detailed_description":"","developers":["Different Tales"],"fullgame":{"appid":"2463980","name":"Werewolf: The Apocalypse \u2014 Purgatory"},"header_image":"https://shared.akamai.steamstatic.com/store_item_assets/steam/apps/2821430/header.jpg?t=1716663613","is_free":true,"linux_requirements":{"minimum":"<strong>Minimum:</strong><br><ul class=\"bb_ul\"><li><strong>Processor:</strong> Dual core or better<br></li><li><strong>Memory:</strong> 4 GB RAM<br></li><li><strong>Graphics:</strong> Intel\u00ae HD 4400 or better<br></li><li><strong>Storage:</strong> 500 GB available space</li></ul>","recommended":"<strong>Recommended:</strong><br><ul class=\"bb_ul\"></ul>"},"mac_requirements":{"minimum":"<strong>Minimum:</strong><br><ul class=\"bb_ul\"><li><strong>OS:</strong> MacOS Sierra<br></li><li><strong>Processor:</strong> Dual core or better<br></li><li><strong>Memory:</strong> 4 GB RAM<br></li><li><strong>Graphics:</strong> Intel\u00ae HD 6000 or better<br></li><li><strong>Storage:</strong> 500 MB available space</li></ul>","recommended":"<strong>Recommended:</strong><br><ul class=\"bb_ul\"></ul>"},"name":"Werewolf: The Apocalypse \u2014 Purgatory DEMO","package_groups":[],"pc_requirements":{"minimum":"<strong>Minimum:</strong><br><ul class=\"bb_ul\"><li>Requires a 64-bit processor and operating system<br></li><li><strong>OS *:</strong> Windows 7, 8.1, 10 (64-bit)<br></li><li><strong>Processor:</strong> Windows 7, 8.1, 10 (64-bit)<br></li><li><strong>Memory:</strong> 4 GB RAM<br></li><li><strong>Graphics:</strong> Intel\u00ae HD 4400 or better<br></li><li><strong>DirectX:</strong> Version 11<br></li><li><strong>Storage:</strong> 500 MB available space</li></ul>","recommended":"<strong>Recommended:</strong><br><ul class=\"bb_ul\"><li>Requires a 64-bit processor and operating system</li></ul>"},"platforms":{"linux":true,"mac":true,"windows":true},"publishers":["Different Tales"],"ratings":{"dejus":{"banned":"0","descriptors":"Viol\u00eancia Extrema\nLinguagem impr\u00f3pria\nMedo","rating":"16","rating_generated":"1","required_age":"16","use_age_gate":"0"},"steam_germany":{"banned":"0","descriptors":"Drastische Gewalt\nAlkohol / Tabak\nDerbe Sprache","rating":"18","rating_generated":"1","required_age":"18","use_age_gate":"0"}},"release_date":{"coming_soon":false,"date":"25 May, 2024"},"required_age":0,"screenshots":[{"id":0,"path_full":"https://shared.akamai.steamstatic.com/store_item_assets/steam/apps/2821430/ss_ba377f083e7f746873311fb95fdee1fea3bba9b5.1920x1080.jpg?t=1716663613","path_thumbnail":"https://shared.akamai.steamstatic.com/store_item_assets/steam/apps/2821430/ss_ba377f083e7f746873311fb95fdee1fea3bba9b5.600x338.jpg?t=1716663613"},{"id":1,"path_full":"https://shared.akamai.steamstatic.com/store_item_assets/steam/apps/2821430/ss_c5d96626268e580e134bd0c4da361bda9995b51b.1920x1080.jpg?t=1716663613","path_thumbnail":"https://shared.akamai.steamstatic.com/store_item_assets/steam/apps/2821430/ss_c5d96626268e580e134bd0c4da361bda9995b51b.600x338.jpg?t=1716663613"},{"id":2,"path_full":"https://shared.akamai.steamstatic.com/store_item_assets/steam/apps/2821430/ss_d61d74a3a8fd8f0683920a0452e3b7813b93a2f9.1920x1080.jpg?t=1716663613","path_thumbnail":"https://shared.akamai.steamstatic.com/store_item_assets/steam/apps/2821430/ss_d61d74a3a8fd8f0683920a0452e3b7813b93a2f9.600x338.jpg?t=1716663613"},{"id":3,"path_full":"https://shared.akamai.steamstatic.com/store_item_assets/steam/apps/2821430/ss_90e1704e9c39ee77389b39e7821e859a01e7eaf1.1920x1080.jpg?t=1716663613","path_thumbnail":"https://shared.akamai.steamstatic.com/store_item_assets/steam/apps/2821430/ss_90e1704e9c39ee77389b39e7821e859a01e7eaf1.600x338.jpg?t=1716663613"},{"id":4,"path_full":"https://shared.akamai.steamstatic.com/store_item_assets/steam/apps/2821430/ss_495619ccabbf5b8a66f4c8fd649bfc9dcaa88323.1920x1080.jpg?t=1716663613","path_thumbnail":"https://shared.akamai.steamstatic.com/store_item_assets/steam/apps/2821430/ss_495619ccabbf5b8a66f4c8fd649bfc9dcaa88323.600x338.jpg?t=1716663613"},{"id":5,"path_full":"https://shared.akamai.steamstatic.com/store_item_assets/steam/apps/2821430/ss_068692b9242d0be86a382c0b7d4f8fe6f9cd004d.1920x1080.jpg?t=1716663613","path_thumbnail":"https://shared.akamai.steamstatic.com/store_item_assets/steam/apps/2821430/ss_068692b9242d0be86a382c0b7d4f8fe6f9cd004d.600x338.jpg?t=1716663613"},{"id":6,"path_full":"https://shared.akamai.steamstatic.com/store_item_assets/steam/apps/2821430/ss_a64d4ef9583578756019c34877cc8499dae1f026.1920x1080.jpg?t=1716663613","path_thumbnail":"https://shared.akamai.steamstatic.com/store_item_assets/steam/apps/2821430/ss_a64d4ef9583578756019c34877cc8499dae1f026.600x338.jpg?t=1716663613"},{"id":7,"path_full":"https://shared.akamai.steamstatic.com/store_item_assets/steam/apps/2821430/ss_1cdf3503500ac3e6f390b071ae5982cfd8a57397.1920x1080.jpg?t=1716663613","path_thumbnail":"https://shared.akamai.steamstatic.com/store_item_assets/steam/apps/2821430/ss_1cdf3503500ac3e6f390b071ae5982cfd8a57397.600x338.jpg?t=1716663613"},{"id":8,"path_full":"https://shared.akamai.steamstatic.com/store_item_assets/steam/apps/2821430/ss_fd92defa5dab6df5b1f0697724af391e87dbca9a.1920x1080.jpg?t=1716663613","path_thumbnail":"https://shared.akamai.steamstatic.com/store_item_assets/steam/apps/2821430/ss_fd92defa5dab6df5b1f0697724af391e87dbca9a.600x338.jpg?t=1716663613"},{"id":9,"path_full":"https://shared.akamai.steamstatic.com/store_item_assets/steam/apps/2821430/ss_3e42f3588b301616a68773b33d3f31d05db91d9d.1920x1080.jpg?t=1716663613","path_thumbnail":"https://shared.akamai.steamstatic.com/store_item_assets/steam/apps/2821430/ss_3e42f3588b301616a68773b33d3f31d05db91d9d.600x338.jpg?t=1716663613"},{"id":10,"path_full":"https://shared.akamai.steamstatic.com/store_item_assets/steam/apps/2821430/ss_a8fcf5af47a2616753d66ae9a1a469f98ced0c8b.1920x1080.jpg?t=1716663613","path_thumbnail":"https://shared.akamai.steamstatic.com/store_item_assets/steam/apps/2821430/ss_a8fcf5af47a2616753d66ae9a1a469f98ced0c8b.600x338.jpg?t=1716663613"}],"short_description":"","steam_appid":2821430,"support_info":{"email":"support@differenttales.com","url":"http://differenttales.com"},"supported_languages":"English","type":"demo","website":"http://differenttales.com/werewolf/"}