{"about_the_game":"\u203bThe personal independent parkour game &quot;Hustle Game V1&quot; is a game that combines parkour and combat elements. It is based on the theme of the Time Administration. Players will play a member of a special task force, traveling through various time and space scenes, executing mission and protect the stability of the timeline. Multiple scenes (ancient style, cyber, fantasy, ink painting) + multiple mechanisms (parkour, racing, survival, combat)<br />\r\n<br />\r\n\u203bParkour Challenge: Launch parkour challenges in time and space scenes of different styles such as Chinese style, cyberpunk, fantasy, etc. Players need to run, jump, roll in high-rise buildings, ancient city streets, future technology cities and other scenes, avoid obstacles and enemy pursuits, and reach the end as quickly as possible.<br />\r\n<br />\r\n\u203bCombat missions: During the parkour process, players will encounter various enemies, including invaders from other time and space, evil forces that destroy the timeline, etc. Players can perform combat actions such as close combat and long-range attacks to engage in fierce battles with enemies and protect the safety of mission targets.<br />\r\n<br />\r\n\u203bDiverse time and space scenes: The game has rich and colorful time and space scenes. Players can freely travel through scenes such as ancient China, future technology cities, and the fantasy world of myths and legends, and experience different cultural atmospheres and beautiful scene designs; personalized characters Customization: Players can customize the character's appearance and equipment to create their own agent image, choose weapons and skills that suit their own style, and improve their combat capabilities.","background":"https://shared.akamai.steamstatic.com/store_item_assets/steam/apps/2871740/page_bg_generated_v6b.jpg?t=1714181309","background_raw":"https://shared.akamai.steamstatic.com/store_item_assets/steam/apps/2871740/page_bg_generated.jpg?t=1714181309","capsule_image":"https://shared.akamai.steamstatic.com/store_item_assets/steam/apps/2871740/capsule_231x87.jpg?t=1714181309","capsule_imagev5":"https://shared.akamai.steamstatic.com/store_item_assets/steam/apps/2871740/capsule_184x69.jpg?t=1714181309","categories":[{"description":"Single-player","id":2},{"description":"Family Sharing","id":62}],"content_descriptors":{"ids":[],"notes":null},"detailed_description":"\u203bThe personal independent parkour game &quot;Hustle Game V1&quot; is a game that combines parkour and combat elements. It is based on the theme of the Time Administration. Players will play a member of a special task force, traveling through various time and space scenes, executing mission and protect the stability of the timeline. Multiple scenes (ancient style, cyber, fantasy, ink painting) + multiple mechanisms (parkour, racing, survival, combat)<br />\r\n<br />\r\n\u203bParkour Challenge: Launch parkour challenges in time and space scenes of different styles such as Chinese style, cyberpunk, fantasy, etc. Players need to run, jump, roll in high-rise buildings, ancient city streets, future technology cities and other scenes, avoid obstacles and enemy pursuits, and reach the end as quickly as possible.<br />\r\n<br />\r\n\u203bCombat missions: During the parkour process, players will encounter various enemies, including invaders from other time and space, evil forces that destroy the timeline, etc. Players can perform combat actions such as close combat and long-range attacks to engage in fierce battles with enemies and protect the safety of mission targets.<br />\r\n<br />\r\n\u203bDiverse time and space scenes: The game has rich and colorful time and space scenes. Players can freely travel through scenes such as ancient China, future technology cities, and the fantasy world of myths and legends, and experience different cultural atmospheres and beautiful scene designs; personalized characters Customization: Players can customize the character's appearance and equipment to create their own agent image, choose weapons and skills that suit their own style, and improve their combat capabilities.","developers":["VedaLayout"],"genres":[{"description":"Action","id":"1"},{"description":"Adventure","id":"25"},{"description":"Casual","id":"4"},{"description":"Indie","id":"23"}],"header_image":"https://shared.akamai.steamstatic.com/store_item_assets/steam/apps/2871740/header.jpg?t=1714181309","is_free":false,"linux_requirements":{"minimum":"<strong>Minimum:</strong><br><ul class=\"bb_ul\"></ul>","recommended":"<strong>Recommended:</strong><br><ul class=\"bb_ul\"></ul>"},"mac_requirements":{"minimum":"<strong>Minimum:</strong><br><ul class=\"bb_ul\"></ul>","recommended":"<strong>Recommended:</strong><br><ul class=\"bb_ul\"></ul>"},"movies":[{"highlight":true,"id":257004935,"mp4":{"480":"http://video.akamai.steamstatic.com/store_trailers/257004935/movie480.mp4?t=1710382990","max":"http://video.akamai.steamstatic.com/store_trailers/257004935/movie_max.mp4?t=1710382990"},"name":"HustleGame LevelTest 01","thumbnail":"https://shared.akamai.steamstatic.com/store_item_assets/steam/apps/257004935/movie.293x165.jpg?t=1710382990","webm":{"480":"http://video.akamai.steamstatic.com/store_trailers/257004935/movie480_vp9.webm?t=1710382990","max":"http://video.akamai.steamstatic.com/store_trailers/257004935/movie_max_vp9.webm?t=1710382990"}},{"highlight":true,"id":257004927,"mp4":{"480":"http://video.akamai.steamstatic.com/store_trailers/257004927/movie480.mp4?t=1710382995","max":"http://video.akamai.steamstatic.com/store_trailers/257004927/movie_max.mp4?t=1710382995"},"name":"HustleGamePreview","thumbnail":"https://shared.akamai.steamstatic.com/store_item_assets/steam/apps/257004927/movie.293x165.jpg?t=1710382995","webm":{"480":"http://video.akamai.steamstatic.com/store_trailers/257004927/movie480_vp9.webm?t=1710382995","max":"http://video.akamai.steamstatic.com/store_trailers/257004927/movie_max_vp9.webm?t=1710382995"}},{"highlight":true,"id":257004945,"mp4":{"480":"http://video.akamai.steamstatic.com/store_trailers/257004945/movie480.mp4?t=1710383000","max":"http://video.akamai.steamstatic.com/store_trailers/257004945/movie_max.mp4?t=1710383000"},"name":"HustleGame LevelTest 02","thumbnail":"https://shared.akamai.steamstatic.com/store_item_assets/steam/apps/257004945/movie.293x165.jpg?t=1710383000","webm":{"480":"http://video.akamai.steamstatic.com/store_trailers/257004945/movie480_vp9.webm?t=1710383000","max":"http://video.akamai.steamstatic.com/store_trailers/257004945/movie_max_vp9.webm?t=1710383000"}},{"highlight":true,"id":257004963,"mp4":{"480":"http://video.akamai.steamstatic.com/store_trailers/257004963/movie480.mp4?t=1710383005","max":"http://video.akamai.steamstatic.com/store_trailers/257004963/movie_max.mp4?t=1710383005"},"name":"HustleGame LevelTest 03","thumbnail":"https://shared.akamai.steamstatic.com/store_item_assets/steam/apps/257004963/movie.293x165.jpg?t=1710383005","webm":{"480":"http://video.akamai.steamstatic.com/store_trailers/257004963/movie480_vp9.webm?t=1710383005","max":"http://video.akamai.steamstatic.com/store_trailers/257004963/movie_max_vp9.webm?t=1710383005"}}],"name":"HustleGame","package_groups":[{"description":"","display_type":0,"is_recurring_subscription":"false","name":"default","save_text":"","selection_text":"Select a purchase option","subs":[{"can_get_free_license":"0","is_free_license":false,"option_description":"","option_text":"TheHustleGame - $4.99 USD","packageid":1024121,"percent_savings":0,"percent_savings_text":" ","price_in_cents_with_discount":499}],"title":"Buy HustleGame"}],"packages":[1024121],"pc_requirements":{"minimum":"<strong>Minimum:</strong><br><ul class=\"bb_ul\"><li>Requires a 64-bit processor and operating system<br></li><li><strong>OS:</strong> Windows10<br></li><li><strong>Memory:</strong> 4 GB RAM</li></ul>","recommended":"<strong>Recommended:</strong><br><ul class=\"bb_ul\"><li>Requires a 64-bit processor and operating system<br></li><li><strong>OS:</strong> Windows10<br></li><li><strong>Memory:</strong> 4 GB RAM</li></ul>"},"platforms":{"linux":false,"mac":false,"windows":true},"price_overview":{"currency":"USD","discount_percent":0,"final":499,"final_formatted":"$4.99 USD","initial":499,"initial_formatted":""},"publishers":["VedaLayout"],"ratings":{"dejus":{"banned":"0","descriptors":"Viol\u00eancia fantasiosa","rating":"l","rating_generated":"1","required_age":"0","use_age_gate":"0"},"steam_germany":{"banned":"0","descriptors":"Fantasy-Gewalt","rating":"6","rating_generated":"1","required_age":"6","use_age_gate":"0"}},"release_date":{"coming_soon":false,"date":"26 Apr, 2024"},"required_age":0,"screenshots":[{"id":0,"path_full":"https://shared.akamai.steamstatic.com/store_item_assets/steam/apps/2871740/ss_a581106f55dac5da7a07fb6b4d71a798bad86741.1920x1080.jpg?t=1714181309","path_thumbnail":"https://shared.akamai.steamstatic.com/store_item_assets/steam/apps/2871740/ss_a581106f55dac5da7a07fb6b4d71a798bad86741.600x338.jpg?t=1714181309"},{"id":1,"path_full":"https://shared.akamai.steamstatic.com/store_item_assets/steam/apps/2871740/ss_a9d9342640ef3a9c8f16b2bc8dd222c5d343264b.1920x1080.jpg?t=1714181309","path_thumbnail":"https://shared.akamai.steamstatic.com/store_item_assets/steam/apps/2871740/ss_a9d9342640ef3a9c8f16b2bc8dd222c5d343264b.600x338.jpg?t=1714181309"},{"id":2,"path_full":"https://shared.akamai.steamstatic.com/store_item_assets/steam/apps/2871740/ss_dcf5179b43e3d302fa5d084223f86d1eac0ff2d9.1920x1080.jpg?t=1714181309","path_thumbnail":"https://shared.akamai.steamstatic.com/store_item_assets/steam/apps/2871740/ss_dcf5179b43e3d302fa5d084223f86d1eac0ff2d9.600x338.jpg?t=1714181309"},{"id":3,"path_full":"https://shared.akamai.steamstatic.com/store_item_assets/steam/apps/2871740/ss_abb1fd5fcc0fed798b9cfd91f46184c972a01456.1920x1080.jpg?t=1714181309","path_thumbnail":"https://shared.akamai.steamstatic.com/store_item_assets/steam/apps/2871740/ss_abb1fd5fcc0fed798b9cfd91f46184c972a01456.600x338.jpg?t=1714181309"},{"id":4,"path_full":"https://shared.akamai.steamstatic.com/store_item_assets/steam/apps/2871740/ss_b7d50eb7ce8e1a634773c5b505b44c704a7b1355.1920x1080.jpg?t=1714181309","path_thumbnail":"https://shared.akamai.steamstatic.com/store_item_assets/steam/apps/2871740/ss_b7d50eb7ce8e1a634773c5b505b44c704a7b1355.600x338.jpg?t=1714181309"},{"id":5,"path_full":"https://shared.akamai.steamstatic.com/store_item_assets/steam/apps/2871740/ss_4a1953efeb70e603e2d30985f23086a6c9774929.1920x1080.jpg?t=1714181309","path_thumbnail":"https://shared.akamai.steamstatic.com/store_item_assets/steam/apps/2871740/ss_4a1953efeb70e603e2d30985f23086a6c9774929.600x338.jpg?t=1714181309"},{"id":6,"path_full":"https://shared.akamai.steamstatic.com/store_item_assets/steam/apps/2871740/ss_ffda62d1411fe33ce9e3a84d51253b334fd99046.1920x1080.jpg?t=1714181309","path_thumbnail":"https://shared.akamai.steamstatic.com/store_item_assets/steam/apps/2871740/ss_ffda62d1411fe33ce9e3a84d51253b334fd99046.600x338.jpg?t=1714181309"}],"short_description":"&quot;Xuyu HustleGame V1&quot; is a game that combines parkour and combat. By blending parkour and combat elements, a game experience full of excitement and challenges is created, allowing players to experience endless fun and adventure on their journey to protect the timeline.","steam_appid":2871740,"support_info":{"email":"103275642@qq.com","url":""},"supported_languages":"Simplified Chinese<strong>*</strong><br><strong>*</strong>languages with full audio support","type":"game","website":null}