{"about_the_game":"<p class=\"bb_paragraph\">This DLC contains lovely spring clothing that accentuates Foris' sweet and lively side! </p><p class=\"bb_paragraph\"> </p><h2 class=\"bb_tag\">Contents</h2><ul class=\"bb_ul\"><li><p class=\"bb_paragraph\"> 5 outfits: Lovecore, Angel, Bee, Cherry Blossom, and Bunny!</p></li><li><p class=\"bb_paragraph\"> 35+ pieces of clothing </p></li><li><p class=\"bb_paragraph\"> 5 additional challenges </p></li></ul>","background":"https://store.akamai.steamstatic.com/images/storepagebackground/app/3045950?t=1739530782","background_raw":"https://shared.akamai.steamstatic.com/store_item_assets/steam/apps/3045950/page_bg_raw.jpg?t=1739530782","capsule_image":"https://shared.akamai.steamstatic.com/store_item_assets/steam/apps/3045950/43932f28d4b6eb49d9b57828b947642d3724df9a/capsule_231x87.jpg?t=1739530782","capsule_imagev5":"https://shared.akamai.steamstatic.com/store_item_assets/steam/apps/3045950/43932f28d4b6eb49d9b57828b947642d3724df9a/capsule_184x69.jpg?t=1739530782","categories":[{"description":"Single-player","id":2},{"description":"Downloadable Content","id":21},{"description":"Steam Achievements","id":22},{"description":"Full controller support","id":28},{"description":"Steam Cloud","id":23}],"content_descriptors":{"ids":[],"notes":null},"controller_support":"full","detailed_description":"<p class=\"bb_paragraph\">This DLC contains lovely spring clothing that accentuates Foris' sweet and lively side! </p><p class=\"bb_paragraph\"> </p><h2 class=\"bb_tag\">Contents</h2><ul class=\"bb_ul\"><li><p class=\"bb_paragraph\"> 5 outfits: Lovecore, Angel, Bee, Cherry Blossom, and Bunny!</p></li><li><p class=\"bb_paragraph\"> 35+ pieces of clothing </p></li><li><p class=\"bb_paragraph\"> 5 additional challenges </p></li></ul>","developers":["KigyoDev"],"fullgame":{"appid":"2924880","name":"Artificial Fashionista"},"genres":[{"description":"Casual","id":"4"},{"description":"Indie","id":"23"},{"description":"Simulation","id":"28"},{"description":"Free To Play","id":"37"}],"header_image":"https://shared.akamai.steamstatic.com/store_item_assets/steam/apps/3045950/header.jpg?t=1739530782","is_free":false,"linux_requirements":[],"mac_requirements":[],"name":"Artificial Fashionista - Spring Collection","package_groups":[{"description":"","display_type":0,"is_recurring_subscription":"false","name":"default","save_text":"","selection_text":"Select a purchase option","subs":[{"can_get_free_license":"0","is_free_license":false,"option_description":"","option_text":"Artificial Fashionista - Spring Collection - $2.99 USD","packageid":1082704,"percent_savings":0,"percent_savings_text":" ","price_in_cents_with_discount":299}],"title":"Buy Artificial Fashionista - Spring Collection"}],"packages":[1082704],"pc_requirements":[],"platforms":{"linux":true,"mac":true,"windows":true},"price_overview":{"currency":"USD","discount_percent":0,"final":299,"final_formatted":"$2.99 USD","initial":299,"initial_formatted":""},"publishers":["KigyoDev"],"ratings":{"dejus":{"banned":"0","descriptors":"Conte\u00fado sexual","rating":"12","rating_generated":"1","required_age":"12","use_age_gate":"0"},"steam_germany":{"banned":"0","descriptors":"Sexuelle Andeutungen","rating":"12","rating_generated":"1","required_age":"12","use_age_gate":"0"}},"release_date":{"coming_soon":false,"date":"14 Feb, 2025"},"required_age":0,"screenshots":[{"id":0,"path_full":"https://shared.akamai.steamstatic.com/store_item_assets/steam/apps/3045950/ss_cf9be8d0ea85688ca938ea20d0367ad7ddd3179c.1920x1080.jpg?t=1739530782","path_thumbnail":"https://shared.akamai.steamstatic.com/store_item_assets/steam/apps/3045950/ss_cf9be8d0ea85688ca938ea20d0367ad7ddd3179c.600x338.jpg?t=1739530782"},{"id":1,"path_full":"https://shared.akamai.steamstatic.com/store_item_assets/steam/apps/3045950/ss_7c53d76c39a499357da2c1e1b8fe5330bb6ee06c.1920x1080.jpg?t=1739530782","path_thumbnail":"https://shared.akamai.steamstatic.com/store_item_assets/steam/apps/3045950/ss_7c53d76c39a499357da2c1e1b8fe5330bb6ee06c.600x338.jpg?t=1739530782"},{"id":2,"path_full":"https://shared.akamai.steamstatic.com/store_item_assets/steam/apps/3045950/ss_fec1a58422e711c455570ce4e63ebe0ff9048d57.1920x1080.jpg?t=1739530782","path_thumbnail":"https://shared.akamai.steamstatic.com/store_item_assets/steam/apps/3045950/ss_fec1a58422e711c455570ce4e63ebe0ff9048d57.600x338.jpg?t=1739530782"},{"id":3,"path_full":"https://shared.akamai.steamstatic.com/store_item_assets/steam/apps/3045950/ss_cc45a437e9873f7e612719c24048e11ec1d68b16.1920x1080.jpg?t=1739530782","path_thumbnail":"https://shared.akamai.steamstatic.com/store_item_assets/steam/apps/3045950/ss_cc45a437e9873f7e612719c24048e11ec1d68b16.600x338.jpg?t=1739530782"},{"id":4,"path_full":"https://shared.akamai.steamstatic.com/store_item_assets/steam/apps/3045950/ss_3ce3df1987ea8a568a4c6238f78636674da70277.1920x1080.jpg?t=1739530782","path_thumbnail":"https://shared.akamai.steamstatic.com/store_item_assets/steam/apps/3045950/ss_3ce3df1987ea8a568a4c6238f78636674da70277.600x338.jpg?t=1739530782"},{"id":5,"path_full":"https://shared.akamai.steamstatic.com/store_item_assets/steam/apps/3045950/ss_3dd6e3a50d35791d029d1607f787433fa4219359.1920x1080.jpg?t=1739530782","path_thumbnail":"https://shared.akamai.steamstatic.com/store_item_assets/steam/apps/3045950/ss_3dd6e3a50d35791d029d1607f787433fa4219359.600x338.jpg?t=1739530782"},{"id":6,"path_full":"https://shared.akamai.steamstatic.com/store_item_assets/steam/apps/3045950/ss_afd51723752538ce00d969d867f7eec2594bc1fb.1920x1080.jpg?t=1739530782","path_thumbnail":"https://shared.akamai.steamstatic.com/store_item_assets/steam/apps/3045950/ss_afd51723752538ce00d969d867f7eec2594bc1fb.600x338.jpg?t=1739530782"},{"id":7,"path_full":"https://shared.akamai.steamstatic.com/store_item_assets/steam/apps/3045950/ss_0468e8907c88dad3dce6a566588a3b3abc69e1b8.1920x1080.jpg?t=1739530782","path_thumbnail":"https://shared.akamai.steamstatic.com/store_item_assets/steam/apps/3045950/ss_0468e8907c88dad3dce6a566588a3b3abc69e1b8.600x338.jpg?t=1739530782"}],"short_description":"A set of 35+ new Spring-themed items for Foris to wear!","steam_appid":3045950,"support_info":{"email":"support@kigyodev.com","url":"https://kigyodev.com/#contact"},"supported_languages":"English","type":"dlc","website":"https://kigyodev.com"}