{"about_the_game":"","background":"","background_raw":"","capsule_image":"https://shared.akamai.steamstatic.com/store_item_assets/steam/apps/550290/capsule_231x87.jpg?t=1551467042","capsule_imagev5":"https://shared.akamai.steamstatic.com/store_item_assets/steam/apps/550290/capsule_184x69.jpg?t=1551467042","categories":[{"description":"Full controller support","id":28},{"description":"Native Steam Controller Support","id":33}],"content_descriptors":{"ids":[],"notes":null},"controller_support":"full","detailed_description":"","fullgame":{"appid":"550290","name":"Sailor Moon S Season 3"},"header_image":"https://shared.akamai.steamstatic.com/store_item_assets/steam/apps/556403/header.jpg?t=1553638540","is_free":false,"linux_requirements":[],"mac_requirements":[],"name":"Sailor Moon S Season 3: To Save Our Friends: Moon and Uranus Join Forces","package_groups":[],"pc_requirements":[],"platforms":{"linux":false,"mac":false,"windows":true},"ratings":null,"release_date":{"coming_soon":false,"date":"Nov 15, 2016"},"required_age":0,"short_description":"Realizing that the two mysterious Sailor Guardians Uranus and Neptune are also after the talismans, Kaolinite sends a Daimon to get rid of them for good.","steam_appid":556403,"support_info":{"email":"","url":""},"supported_languages":"English<strong>*</strong><br><strong>*</strong>languages with full audio support","type":"episode","website":null}